{
    "Ar36":{
        "error":0.0002162211,
        "error_type":"SEM",
        "filter_outliers_dict":{
            "filter_outliers":true,
            "iterations":1,
            "std_devs":2
        },
        "fit":"Linear",
        "value":0.0074393603
    },
    "Ar37":{
        "error":0.0095469739,
        "error_type":"SEM",
        "filter_outliers_dict":{
            "filter_outliers":true,
            "iterations":1,
            "std_devs":2
        },
        "fit":"linear",
        "value":0.3404893811
    },
    "Ar38":{
        "error":0.0049801868,
        "error_type":"SEM",
        "filter_outliers_dict":{
            "filter_outliers":true,
            "iterations":1,
            "std_devs":2
        },
        "fit":"linear",
        "value":1.411300321
    },
    "Ar39":{
        "error":0.022585424,
        "error_type":"SEM",
        "filter_outliers_dict":{
            "filter_outliers":true,
            "iterations":1,
            "std_devs":2
        },
        "fit":"Linear",
        "value":112.2558389943
    },
    "Ar40":{
        "error":0.0548942568,
        "error_type":"SEM",
        "filter_outliers_dict":{
            "filter_outliers":true,
            "iterations":1,
            "std_devs":2
        },
        "fit":"Linear",
        "value":914.985260634
    },
    "Ar41":{
        "error":0.0101040747,
        "error_type":"SEM",
        "filter_outliers_dict":{
            "filter_outliers":true,
            "iterations":1,
            "std_devs":2
        },
        "fit":"Average",
        "value":0.0525361057
    }
}